odoo/addons/l10n_ro_config/README.rst
odoo/addons/l10n_ro_config/__init__.py
odoo/addons/l10n_ro_config/__manifest__.py
odoo/addons/l10n_ro_config/init_hook.py
odoo/addons/l10n_ro_config/controllers/__init__.py
odoo/addons/l10n_ro_config/controllers/main.py
odoo/addons/l10n_ro_config/i18n/l10n_ro_config.pot
odoo/addons/l10n_ro_config/i18n/ro.po
odoo/addons/l10n_ro_config/migrations/14.0.1.5.1/pre-migration.py
odoo/addons/l10n_ro_config/migrations/14.0.2.10.1/pre-migration.py
odoo/addons/l10n_ro_config/models/__init__.py
odoo/addons/l10n_ro_config/models/account_journal.py
odoo/addons/l10n_ro_config/models/ir_ui_menu.py
odoo/addons/l10n_ro_config/models/l10n_ro_mixin.py
odoo/addons/l10n_ro_config/models/product_template.py
odoo/addons/l10n_ro_config/models/res_bank.py
odoo/addons/l10n_ro_config/models/res_company.py
odoo/addons/l10n_ro_config/models/res_config_settings.py
odoo/addons/l10n_ro_config/models/res_partner.py
odoo/addons/l10n_ro_config/readme/CONTRIBUTORS.rst
odoo/addons/l10n_ro_config/readme/DESCRIPTION.rst
odoo/addons/l10n_ro_config/readme/INSTALL.rst
odoo/addons/l10n_ro_config/readme/USAGE.rst
odoo/addons/l10n_ro_config/static/description/icon.png
odoo/addons/l10n_ro_config/static/description/icon.svg
odoo/addons/l10n_ro_config/static/description/index.html
odoo/addons/l10n_ro_config/tests/__init__.py
odoo/addons/l10n_ro_config/tests/test_bank_account_print_report.py
odoo/addons/l10n_ro_config/tests/test_partner_country_code.py
odoo/addons/l10n_ro_config/views/account_journal.xml
odoo/addons/l10n_ro_config/views/common_report.xml
odoo/addons/l10n_ro_config/views/res_bank_view.xml
odoo/addons/l10n_ro_config/views/res_config_view.xml
odoo/addons/l10n_ro_config/views/res_partner_view.xml
odoo/addons/l10n_ro_config/views/webclient_templates.xml
odoo14_addon_l10n_ro_config-14.0.2.17.0.dist-info/METADATA
odoo14_addon_l10n_ro_config-14.0.2.17.0.dist-info/WHEEL
odoo14_addon_l10n_ro_config-14.0.2.17.0.dist-info/top_level.txt
odoo14_addon_l10n_ro_config-14.0.2.17.0.dist-info/RECORD
